fvar/__init__.py
fvar/fv.py
fvar/fv1.py
fvar-0.0.1.dist-info/LICENSE
fvar-0.0.1.dist-info/METADATA
fvar-0.0.1.dist-info/WHEEL
fvar-0.0.1.dist-info/top_level.txt
fvar-0.0.1.dist-info/RECORD
